komPYoot/__init__.py
komPYoot/api.py
komPYoot-1.0.5.data/data/requirements.txt
komPYoot-1.0.5.dist-info/LICENSE
komPYoot-1.0.5.dist-info/METADATA
komPYoot-1.0.5.dist-info/WHEEL
komPYoot-1.0.5.dist-info/top_level.txt
komPYoot-1.0.5.dist-info/RECORD
