Metadata-Version: 2.1
Name: komPYoot
Version: 1.0.5
Summary: Python Interface for Komoot API
Home-page: https://github.com/matiyau/komPYoot
Author: Nishad Mandlik
Author-email: mandliksg@gmail.com
Project-URL: Documentation, https://komPYoot.rtfd.io
Project-URL: Bug Tracker, https://github.com/matiyau/komPYoot/issues
Classifier: Programming Language :: Python :: 3
Classifier: License :: OSI Approved :: MIT License
Classifier: Operating System :: OS Independent
Requires-Python: >=3.10
License-File: LICENSE
